langfuzz/__init__.py
langfuzz/redteam.py
langfuzz-0.0.2.dist-info/LICENSE
langfuzz-0.0.2.dist-info/METADATA
langfuzz-0.0.2.dist-info/WHEEL
langfuzz-0.0.2.dist-info/entry_points.txt
langfuzz-0.0.2.dist-info/top_level.txt
langfuzz-0.0.2.dist-info/RECORD
