Metadata-Version: 2.1
Name: langfuzz
Version: 0.0.2
Summary: Project to fuzz language model applications
Author: Harrison Chase
License-File: LICENSE
Requires-Dist: langgraph
Requires-Dist: langchain
Requires-Dist: langchain-openai
Requires-Dist: langsmith
Requires-Dist: pyyaml
